{
  "version": "7",
  "dialect": "sqlite",
  "entries": [
    {
      "idx": 0,
      "version": "6",
      "when": 1772832455001,
      "tag": "0000_illegal_butterfly",
      "breakpoints": true
    },
    {
      "idx": 1,
      "version": "6",
      "when": 1772875629205,
      "tag": "0001_crazy_magneto",
      "breakpoints": true
    },
    {
      "idx": 2,
      "version": "6",
      "when": 1772902156928,
      "tag": "0002_tricky_master_mold",
      "breakpoints": true
    },
    {
      "idx": 3,
      "version": "6",
      "when": 1773039761313,
      "tag": "0003_foamy_rockslide",
      "breakpoints": true
    },
    {
      "idx": 4,
      "version": "6",
      "when": 1773049625371,
      "tag": "0004_faithful_sprite",
      "breakpoints": true
    }
  ]
}